asgi_s3_response_middleware/__init__.py
asgi_s3_response_middleware/middleware.py
asgi_s3_response_middleware/utils.py
asgi_s3_response_middleware-0.0.4.dist-info/WHEEL
asgi_s3_response_middleware-0.0.4.dist-info/METADATA
asgi_s3_response_middleware-0.0.4.dist-info/licenses/LICENSE
asgi_s3_response_middleware-0.0.4.dist-info/RECORD
