Metadata-Version: 2.1
Name: asgi_s3_response_middleware
Version: 0.0.4
Summary: Middleware to spill large responses over to S3.
Author-email: Anthony Lukach <anthony@developmentseed.org>
Maintainer-email: Anthony Lukach <anthony@developmentseed.org>
Requires-Python: >=3.8
Requires-Dist: boto3>=1.35.11
Requires-Dist: httpx>=0.27.2
Requires-Dist: starlette>=0.38.4
Provides-Extra: lint
Requires-Dist: pre-commit; extra == "lint"
Provides-Extra: testing
Requires-Dist: boto3-stubs[s3]>=1.35.11; extra == "testing"
Requires-Dist: coverage; extra == "testing"
Requires-Dist: moto>=5.0.13; extra == "testing"
Requires-Dist: pytest; extra == "testing"
